{
  "comment": {
    "_expands": [
      "attachment",
      "renderedBody"
    ],
    "id": "1000",
    "body": "Please find the screenshot and the log file attached. !screenshot.png|thumbnail! [^log.txt] _(32 kB)_",
    "public": true,
    "author": {
      "accountId": "qm:a713c8ea-1075-4e30-9d96-891a7d181739:5ad6d3581db05e2a66fa80b",
      "name": "qm:a713c8ea-1075-4e30-9d96-891a7d181739:5ad6d3581db05e2a66fa80b",
      "key": "qm:a713c8ea-1075-4e30-9d96-891a7d181739:5ad6d3581db05e2a66fa80b",
      "emailAddress": "fred@example.com",
      "displayName": "Fred F. User",
      "active": true,
      "timeZone": "Australia/Sydney",
      "_links": {
        "jiraRest": "https://your-domain.atlassian.net/rest/api/2/user?username=qm:a713c8ea-1075-4e30-9d96-891a7d181739:5ad6d3581db05e2a66fa80b",
        "avatarUrls": {
          "48x48": "https://avatar-cdn.atlassian.com/9bc3b5bcb0db050c6d7660b28a5b86c9?s=48&d=https%3A%2F%2Fsecure.gravatar.com%2Favatar%2F9bc3b5bcb0db050c6d7660b28a5b86c9%3Fd%3Dmm%26s%3D48%26noRedirect%3Dtrue",
          "24x24": "https://avatar-cdn.atlassian.com/9bc3b5bcb0db050c6d7660b28a5b86c9?s=24&d=https%3A%2F%2Fsecure.gravatar.com%2Favatar%2F9bc3b5bcb0db050c6d7660b28a5b86c9%3Fd%3Dmm%26s%3D24%26noRedirect%3Dtrue",
          "16x16": "https://avatar-cdn.atlassian.com/9bc3b5bcb0db050c6d7660b28a5b86c9?s=16&d=https%3A%2F%2Fsecure.gravatar.com%2Favatar%2F9bc3b5bcb0db050c6d7660b28a5b86c9%3Fd%3Dmm%26s%3D16%26noRedirect%3Dtrue",
          "32x32": "https://avatar-cdn.atlassian.com/9bc3b5bcb0db050c6d7660b28a5b86c9?s=32&d=https%3A%2F%2Fsecure.gravatar.com%2Favatar%2F9bc3b5bcb0db050c6d7660b28a5b86c9%3Fd%3Dmm%26s%3D32%26noRedirect%3Dtrue"
        },
        "self": "https://your-domain.atlassian.net/rest/api/2/user?username=qm:a713c8ea-1075-4e30-9d96-891a7d181739:5ad6d3581db05e2a66fa80b"
      }
    },
    "created": {
      "iso8601": "2015-10-09T10:22:00+0700",
      "jira": "2015-10-09T10:22:00.000+0700",
      "friendly": "Today 10:22 AM",
      "epochMillis": 1444360920000
    },
    "_links": {
      "self": "https://your-domain.atlassian.net/rest/servicedeskapi/request/2000/comment/1000"
    }
  },
  "attachments": {
    "_expands": [],
    "size": 2,
    "start": 2,
    "limit": 2,
    "isLastPage": false,
    "_links": {
      "base": "https://your-domain.atlassian.net/rest/servicedeskapi",
      "context": "context",
      "next": "https://your-domain.atlassian.net/rest/servicedeskapi/request/IT-15/comment/1001/attachment?start=4&limit=2",
      "prev": "https://your-domain.atlassian.net/rest/servicedeskapi/request/IT-15/comment/1001/attachment?start=0&limit=2"
    },
    "values": [
      {
        "filename": "screenshot.png",
        "author": {
          "accountId": "qm:a713c8ea-1075-4e30-9d96-891a7d181739:5ad6d3581db05e2a66fa80b",
          "name": "qm:a713c8ea-1075-4e30-9d96-891a7d181739:5ad6d3581db05e2a66fa80b",
          "key": "qm:a713c8ea-1075-4e30-9d96-891a7d181739:5ad6d3581db05e2a66fa80b",
          "emailAddress": "fred@example.com",
          "displayName": "Fred F. User",
          "active": true,
          "timeZone": "Australia/Sydney",
          "_links": {
            "jiraRest": "https://your-domain.atlassian.net/rest/api/2/user?username=qm:a713c8ea-1075-4e30-9d96-891a7d181739:5ad6d3581db05e2a66fa80b",
            "avatarUrls": {
              "48x48": "https://avatar-cdn.atlassian.com/9bc3b5bcb0db050c6d7660b28a5b86c9?s=48&d=https%3A%2F%2Fsecure.gravatar.com%2Favatar%2F9bc3b5bcb0db050c6d7660b28a5b86c9%3Fd%3Dmm%26s%3D48%26noRedirect%3Dtrue",
              "24x24": "https://avatar-cdn.atlassian.com/9bc3b5bcb0db050c6d7660b28a5b86c9?s=24&d=https%3A%2F%2Fsecure.gravatar.com%2Favatar%2F9bc3b5bcb0db050c6d7660b28a5b86c9%3Fd%3Dmm%26s%3D24%26noRedirect%3Dtrue",
              "16x16": "https://avatar-cdn.atlassian.com/9bc3b5bcb0db050c6d7660b28a5b86c9?s=16&d=https%3A%2F%2Fsecure.gravatar.com%2Favatar%2F9bc3b5bcb0db050c6d7660b28a5b86c9%3Fd%3Dmm%26s%3D16%26noRedirect%3Dtrue",
              "32x32": "https://avatar-cdn.atlassian.com/9bc3b5bcb0db050c6d7660b28a5b86c9?s=32&d=https%3A%2F%2Fsecure.gravatar.com%2Favatar%2F9bc3b5bcb0db050c6d7660b28a5b86c9%3Fd%3Dmm%26s%3D32%26noRedirect%3Dtrue"
            },
            "self": "https://your-domain.atlassian.net/rest/api/2/user?username=qm:a713c8ea-1075-4e30-9d96-891a7d181739:5ad6d3581db05e2a66fa80b"
          }
        },
        "created": {
          "iso8601": "2015-10-09T10:22:00+0700",
          "jira": "2015-10-09T10:22:00.000+0700",
          "friendly": "Today 10:22 AM",
          "epochMillis": 1444360920000
        },
        "size": 23123,
        "mimeType": "image/png",
        "_links": {
          "jiraRest": "https://your-domain.atlassian.net/rest/api/2/attachment/10000",
          "content": "https://your-domain.atlassian.net/servicedesk/customershim/secure/attachment/10000/screenshot.png",
          "thumbnail": "https://your-domain.atlassian.net/servicedesk/customershim/secure/thumbnail/10000/_thumb_10000.png"
        }
      },
      {
        "filename": "log.txt",
        "author": {
          "accountId": "qm:a713c8ea-1075-4e30-9d96-891a7d181739:5ad6d3581db05e2a66fa80b",
          "name": "qm:a713c8ea-1075-4e30-9d96-891a7d181739:5ad6d3581db05e2a66fa80b",
          "key": "qm:a713c8ea-1075-4e30-9d96-891a7d181739:5ad6d3581db05e2a66fa80b",
          "emailAddress": "fred@example.com",
          "displayName": "Fred F. User",
          "active": true,
          "timeZone": "Australia/Sydney",
          "_links": {
            "jiraRest": "https://your-domain.atlassian.net/rest/api/2/user?username=qm:a713c8ea-1075-4e30-9d96-891a7d181739:5ad6d3581db05e2a66fa80b",
            "avatarUrls": {
              "48x48": "https://avatar-cdn.atlassian.com/9bc3b5bcb0db050c6d7660b28a5b86c9?s=48&d=https%3A%2F%2Fsecure.gravatar.com%2Favatar%2F9bc3b5bcb0db050c6d7660b28a5b86c9%3Fd%3Dmm%26s%3D48%26noRedirect%3Dtrue",
              "24x24": "https://avatar-cdn.atlassian.com/9bc3b5bcb0db050c6d7660b28a5b86c9?s=24&d=https%3A%2F%2Fsecure.gravatar.com%2Favatar%2F9bc3b5bcb0db050c6d7660b28a5b86c9%3Fd%3Dmm%26s%3D24%26noRedirect%3Dtrue",
              "16x16": "https://avatar-cdn.atlassian.com/9bc3b5bcb0db050c6d7660b28a5b86c9?s=16&d=https%3A%2F%2Fsecure.gravatar.com%2Favatar%2F9bc3b5bcb0db050c6d7660b28a5b86c9%3Fd%3Dmm%26s%3D16%26noRedirect%3Dtrue",
              "32x32": "https://avatar-cdn.atlassian.com/9bc3b5bcb0db050c6d7660b28a5b86c9?s=32&d=https%3A%2F%2Fsecure.gravatar.com%2Favatar%2F9bc3b5bcb0db050c6d7660b28a5b86c9%3Fd%3Dmm%26s%3D32%26noRedirect%3Dtrue"
            },
            "self": "https://your-domain.atlassian.net/rest/api/2/user?username=qm:a713c8ea-1075-4e30-9d96-891a7d181739:5ad6d3581db05e2a66fa80b"
          }
        },
        "created": {
          "iso8601": "2015-10-09T10:22:00+0700",
          "jira": "2015-10-09T10:22:00.000+0700",
          "friendly": "Today 10:22 AM",
          "epochMillis": 1444360920000
        },
        "size": 32132,
        "mimeType": "text/plain",
        "_links": {
          "jiraRest": "https://your-domain.atlassian.net/rest/api/2/attachment/10001",
          "content": "https://your-domain.atlassian.net/servicedesk/customershim/secure/attachment/10001/log.txt"
        }
      }
    ]
  }
}